Metadata-Version: 2.4
Name: pretix-xpay
Version: 1.0.20260110.1
Summary: Accept payments through the Nexi's XPay interface
Author-email: Furizon Team <webservice@furizon.net>, Luca Sorace <public.stranck@gmail.com>
Maintainer-email: Furizon Team <webservice@furizon.net>, Luca Sorace <public.stranck@gmail.com>
License: Apache
Project-URL: homepage, https://github.com/APSfurizon/pretix-xpay
Project-URL: repository, https://github.com/APSfurizon/pretix-xpay
Keywords: pretix
License-File: LICENSE
Dynamic: license-file
